organizer/__init__.py
organizer/__main__.py
organizer/engine.py
organizer/interface.py
organizer/utils.py
tidybit2-0.1.7.dist-info/METADATA
tidybit2-0.1.7.dist-info/WHEEL
tidybit2-0.1.7.dist-info/entry_points.txt
tidybit2-0.1.7.dist-info/top_level.txt
tidybit2-0.1.7.dist-info/RECORD
